tle_storage_service/__init__.py
tle_storage_service/alembic.ini
tle_storage_service/db.py
tle_storage_service/handlers.py
tle_storage_service/log.py
tle_storage_service/middlewares.py
tle_storage_service/server.py
tle_storage_service/tle.py
tle_storage_service/web.py
tle_storage_service/migrations/README
tle_storage_service/migrations/env.py
tle_storage_service/migrations/script.py.mako
tle_storage_service/migrations/versions/2017-06-07T15-40-25_f206d1283979_init.py
tle_storage_service/utils/__init__.py
tle_storage_service/utils/common.py
tle_storage_service/utils/pg.py
tle_storage_service-1.0.7.dist-info/DESCRIPTION.rst
tle_storage_service-1.0.7.dist-info/METADATA
tle_storage_service-1.0.7.dist-info/RECORD
tle_storage_service-1.0.7.dist-info/WHEEL
tle_storage_service-1.0.7.dist-info/metadata.json
tle_storage_service-1.0.7.dist-info/top_level.txt
