Metadata-Version: 2.0
Name: tle-storage-service
Version: 1.0.7
Summary: Small aiohttp server application for TLE storage
Home-page: https://github.com/nkoshell/tle-storage-service
Author: nkoshell
Author-email: nikita.koshelev@gmail.com
License: MIT
Download-URL: https://github.com/nkoshell/tle-storage-service/archive/1.0.7.tar.gz
Platform: UNKNOWN
Requires-Dist: aio-nasa-tle-loader (>=1.0.0)
Requires-Dist: aio-space-track-api (>=2.1.1)
Requires-Dist: aiohttp (>=2.1.0)
Requires-Dist: aiopg (>=0.13.0)
Requires-Dist: alembic (>=0.9.2)
Requires-Dist: pyaml (>=16.12.2)
Requires-Dist: sqlalchemy (>=1.1.10)
Requires-Dist: ujson (>=1.35)
